mcp_bridge/__init__.py
mcp_bridge/native_search.py
mcp_bridge/native_watcher.py
mcp_bridge/notifications.py
mcp_bridge/server.py
mcp_bridge/server_tools.py
mcp_bridge/update_manager.py
mcp_bridge/update_manager_pypi.py
mcp_bridge/auth/__init__.py
mcp_bridge/auth/cli.py
mcp_bridge/auth/oauth.py
mcp_bridge/auth/openai_oauth.py
mcp_bridge/auth/token_refresh.py
mcp_bridge/auth/token_store.py
mcp_bridge/cli/__init__.py
mcp_bridge/cli/install_hooks.py
mcp_bridge/cli/session_report.py
mcp_bridge/config/MANIFEST_SCHEMA.md
mcp_bridge/config/README.md
mcp_bridge/config/__init__.py
mcp_bridge/config/hook_config.py
mcp_bridge/config/hooks.py
mcp_bridge/config/hooks_manifest.json
mcp_bridge/config/rate_limits.py
mcp_bridge/config/skills_manifest.json
mcp_bridge/hooks/HOOKS_SETTINGS.json
mcp_bridge/hooks/README.md
mcp_bridge/hooks/__init__.py
mcp_bridge/hooks/agent_reminder.py
mcp_bridge/hooks/auto_slash_command.py
mcp_bridge/hooks/budget_optimizer.py
mcp_bridge/hooks/claude_limits_hook.py
mcp_bridge/hooks/comment_checker.py
mcp_bridge/hooks/compaction.py
mcp_bridge/hooks/context.py
mcp_bridge/hooks/context_monitor.py
mcp_bridge/hooks/delegation_policy.py
mcp_bridge/hooks/dependency_tracker.py
mcp_bridge/hooks/directory_context.py
mcp_bridge/hooks/edit_recovery.py
mcp_bridge/hooks/edit_recovery_policy.py
mcp_bridge/hooks/empty_message_sanitizer.py
mcp_bridge/hooks/events.py
mcp_bridge/hooks/execution_state_tracker.py
mcp_bridge/hooks/git_noninteractive.py
mcp_bridge/hooks/keyword_detector.py
mcp_bridge/hooks/manager.py
mcp_bridge/hooks/notification_hook.py
mcp_bridge/hooks/parallel_enforcement_policy.py
mcp_bridge/hooks/parallel_enforcer.py
mcp_bridge/hooks/parallel_execution.py
mcp_bridge/hooks/parallel_reinforcement_v2.py
mcp_bridge/hooks/pre_compact.py
mcp_bridge/hooks/preemptive_compaction.py
mcp_bridge/hooks/routing_notifications.py
mcp_bridge/hooks/rules_injector.py
mcp_bridge/hooks/session_idle.py
mcp_bridge/hooks/session_notifier.py
mcp_bridge/hooks/session_recovery.py
stravinsky-0.4.74.dist-info/METADATA
stravinsky-0.4.74.dist-info/WHEEL
stravinsky-0.4.74.dist-info/entry_points.txt
stravinsky-0.4.74.dist-info/RECORD
