Metadata-Version: 2.4
Name: stravinsky
Version: 0.4.74
Summary: A sophisticated MCP bridge for Claude Code orchestration
Project-URL: Repository, https://github.com/GratefulDave/stravinsky
Project-URL: Issues, https://github.com/GratefulDave/stravinsky/issues
Author: Stravinsky Team
License: MIT
Keywords: claude,gemini,mcp,oauth,openai
Requires-Python: <3.14,>=3.11
Requires-Dist: aiofiles>=23.1.0
Requires-Dist: chromadb>=0.6.0
Requires-Dist: cryptography>=41.0.0
Requires-Dist: fastapi>=0.128.0
Requires-Dist: google-auth-oauthlib>=1.0.0
Requires-Dist: google-auth>=2.20.0
Requires-Dist: google-genai>=0.2.0
Requires-Dist: httpx>=0.24.0
Requires-Dist: jedi-language-server>=0.41.0
Requires-Dist: jedi>=0.19.2
Requires-Dist: keyring>=25.7.0
Requires-Dist: lsprotocol>=2023.0.0
Requires-Dist: mcp>=1.2.1
Requires-Dist: ollama>=0.6.1
Requires-Dist: openai>=1.0.0
Requires-Dist: pathspec>=0.12.0
Requires-Dist: plyer>=2.1.0
Requires-Dist: psutil>=5.9.0
Requires-Dist: pydantic>=2.0.0
Requires-Dist: pygls>=1.3.0
Requires-Dist: python-dotenv>=1.0.0
Requires-Dist: rank-bm25==0.2.2
Requires-Dist: rich>=13.0.0
Requires-Dist: ruff>=0.14.10
Requires-Dist: tenacity>=8.5.0
Requires-Dist: uvicorn>=0.40.0
Requires-Dist: watchdog~=5.0.0
Provides-Extra: dev
Requires-Dist: mypy>=1.10.0; extra == 'dev'
Requires-Dist: pytest-asyncio>=0.23.0; extra == 'dev'
Requires-Dist: pytest>=8.0.0; extra == 'dev'
Requires-Dist: ruff>=0.4.0; extra == 'dev'
Provides-Extra: semantic
Requires-Dist: chromadb>=0.5.0; extra == 'semantic'
